{
    "bbox": {
        "AP": {
            "mean": 19.62,
            "std": 0.69,
            "conf_95": 0.43,
            "Q1": 19.478654193240587,
            "median": 19.751567850775693,
            "Q3": 20.16043235819336,
            "lowest": 18.26646132518313,
            "lowest_index": 5,
            "highest": 20.477948075916256,
            "highest_index": 8
        },
        "AP50": {
            "mean": 28.06,
            "std": 1.02,
            "conf_95": 0.63,
            "Q1": 27.77522003726285,
            "median": 28.262183328909856,
            "Q3": 28.800793180769332,
            "lowest": 26.03835232429212,
            "lowest_index": 5,
            "highest": 29.350916386934383,
            "highest_index": 8
        },
        "bAP": {
            "mean": 24.13,
            "std": 0.81,
            "conf_95": 0.5,
            "Q1": 23.816379859240897,
            "median": 24.381259529847227,
            "Q3": 24.69768546405141,
            "lowest": 22.65918799925042,
            "lowest_index": 5,
            "highest": 25.00382159932279,
            "highest_index": 6
        },
        "bAP50": {
            "mean": 33.69,
            "std": 1.2,
            "conf_95": 0.75,
            "Q1": 32.97900372711632,
            "median": 34.081215358115216,
            "Q3": 34.57820952934108,
            "lowest": 31.58692743642303,
            "lowest_index": 5,
            "highest": 34.99443739730444,
            "highest_index": 6
        },
        "nAP": {
            "mean": 6.07,
            "std": 0.82,
            "conf_95": 0.51,
            "Q1": 5.643774312304634,
            "median": 6.111009172537019,
            "Q3": 6.794822347987175,
            "lowest": 4.444634362689499,
            "lowest_index": 7,
            "highest": 7.110119010092007,
            "highest_index": 1
        },
        "nAP50": {
            "mean": 11.15,
            "std": 1.43,
            "conf_95": 0.89,
            "Q1": 10.310882290675137,
            "median": 11.346459472825948,
            "Q3": 12.399361619997165,
            "lowest": 8.376313400890114,
            "lowest_index": 7,
            "highest": 12.917776134961038,
            "highest_index": 1
        }
    },
    "segm": {
        "AP": {
            "mean": 18.22,
            "std": 0.66,
            "conf_95": 0.41,
            "Q1": 18.138206630646838,
            "median": 18.295013576021887,
            "Q3": 18.71786509106891,
            "lowest": 16.917501305566958,
            "lowest_index": 5,
            "highest": 19.08051807649133,
            "highest_index": 8
        },
        "AP50": {
            "mean": 27.1,
            "std": 0.99,
            "conf_95": 0.61,
            "Q1": 26.758089517594996,
            "median": 27.278463723718986,
            "Q3": 27.88109249446986,
            "lowest": 25.145938773535637,
            "lowest_index": 5,
            "highest": 28.338790073519803,
            "highest_index": 8
        },
        "bAP": {
            "mean": 22.56,
            "std": 0.77,
            "conf_95": 0.47,
            "Q1": 22.368370856989284,
            "median": 22.781758102468967,
            "Q3": 23.045815487792066,
            "lowest": 21.12531381600005,
            "lowest_index": 5,
            "highest": 23.41371961734024,
            "highest_index": 8
        },
        "bAP50": {
            "mean": 33.25,
            "std": 1.16,
            "conf_95": 0.72,
            "Q1": 32.63736134198945,
            "median": 33.59464703752512,
            "Q3": 34.0616299787303,
            "lowest": 31.155821618862507,
            "lowest_index": 5,
            "highest": 34.554766327841456,
            "highest_index": 6
        },
        "nAP": {
            "mean": 5.19,
            "std": 0.72,
            "conf_95": 0.44,
            "Q1": 5.0588334767813885,
            "median": 5.329533961745032,
            "Q3": 5.5337500963303325,
            "lowest": 3.600764223853894,
            "lowest_index": 7,
            "highest": 6.080913453944616,
            "highest_index": 8
        },
        "nAP50": {
            "mean": 8.65,
            "std": 1.1,
            "conf_95": 0.68,
            "Q1": 8.586524493358839,
            "median": 8.869394729352766,
            "Q3": 9.322443664295275,
            "lowest": 6.219891005031789,
            "lowest_index": 7,
            "highest": 9.90645153322367,
            "highest_index": 8
        }
    }
}